django_settings_diff/__init__.py
django_settings_diff/__main__.py
django_settings_diff/cli.py
django_settings_diff/settingsdiff.py
django_settings_diff-0.2.2.dist-info/entry_points.txt
django_settings_diff-0.2.2.dist-info/LICENSE
django_settings_diff-0.2.2.dist-info/WHEEL
django_settings_diff-0.2.2.dist-info/METADATA
django_settings_diff-0.2.2.dist-info/RECORD
