Metadata-Version: 2.1
Name: django-settings-diff
Version: 0.2.2
Summary: Tool to help diff two Django settings modules
Home-page: http://github.com/GreenBankObservatory/django-settings-diff
License: MIT
Keywords: django,settings,diff
Author: Thomas Chamberlin
Author-email: tchamber@nrao.edu
Requires-Python: >=2.7, !=3.0.*, !=3.1.*, !=3.2.*, !=3.3.*, !=3.4.*
Classifier: Development Status :: 4 - Beta
Classifier: Environment :: Console
Classifier: Intended Audience :: Developers
Classifier: License :: OSI Approved :: MIT License
Classifier: Operating System :: Unix
Classifier: Programming Language :: Python
Classifier: Programming Language :: Python :: 2
Classifier: Programming Language :: Python :: 2.7
Classifier: Programming Language :: Python :: 3
Classifier: Programming Language :: Python :: 3.5
Classifier: Programming Language :: Python :: 3.6
Classifier: Programming Language :: Python :: 3.7
Classifier: Programming Language :: Python :: 3.8
Requires-Dist: deepdiff (>=3.3.0,<4.0.0)
Requires-Dist: django (>=1)
Project-URL: Repository, http://github.com/GreenBankObservatory/django-settings-diff
